HISTORY.md
LICENSE
MANIFEST.in
README.md
setup.py
django_joblog/__init__.py
django_joblog/admin.py
django_joblog/models.py
django_joblog.egg-info/PKG-INFO
django_joblog.egg-info/SOURCES.txt
django_joblog.egg-info/dependency_links.txt
django_joblog.egg-info/not-zip-safe
django_joblog.egg-info/requires.txt
django_joblog.egg-info/top_level.txt
django_joblog/impl/Config.py
django_joblog/impl/DummyJobLogger.py
django_joblog/impl/JobLogger.py
django_joblog/impl/JobLoggerBase.py
django_joblog/impl/JobLoggerContext.py
django_joblog/impl/JobLoggerPingThread.py
django_joblog/impl/JobModelAbstraction.py
django_joblog/impl/__init__.py
django_joblog/impl/exceptions.py
django_joblog/management/__init__.py
django_joblog/management/commands/__init__.py
django_joblog/management/commands/joblog_cleanup.py
django_joblog/management/commands/joblog_list.py
django_joblog/management/commands/joblog_show.py
django_joblog/migrations/0001_initial.py
django_joblog/migrations/0002_alter_state_choices.py
django_joblog/migrations/0003_alter_state_choices.py
django_joblog/migrations/0004_alter_state_choices.py
django_joblog/migrations/__init__.py
django_joblog/tests/__init__.py
django_joblog/tests/t010_basic.py
django_joblog/tests/t020_db_updates.py
django_joblog/tests/t030_parallel.py
django_joblog/tests/t100_regression.py